packaging_demo/__init__.py
packaging_demo/colorized_demo.py
packaging_demo/my_file.py
packaging_demo/my_other_file.py
packaging_demo/slow.py
packaging_demo/states_info.py
packaging_demo_hubzar-1.1.0.dist-info/METADATA
packaging_demo_hubzar-1.1.0.dist-info/WHEEL
packaging_demo_hubzar-1.1.0.dist-info/top_level.txt
packaging_demo_hubzar-1.1.0.dist-info/RECORD
